lef/main.py
lef/utils.py
lef-0.1.5.dist-info/WHEEL
lef-0.1.5.dist-info/METADATA
lef-0.1.5.dist-info/RECORD
