Metadata-Version: 2.1
Name: lef
Version: 0.1.5
Summary: Framework for creating AWS Lambda Extensions
Home-page: https://github.com/lambda-extensions/python-extension-framework
License: MIT
Keywords: AWS,AWS Lambda,Lambda Extensions,Framework,Lambda Extension Framework
Author: Joe Snell
Author-email: joepsnell@gmail.com
Requires-Python: >=3.8,<4.0
Classifier: License :: OSI Approved :: MIT License
Classifier: Programming Language :: Python :: 3
Classifier: Programming Language :: Python :: 3.8
Project-URL: Documentation, https://github.com/lambda-extensions/python-extension-framework
Project-URL: Repository, https://github.com/lambda-extensions/python-extension-framework
